iposi/__init__.py
iposi/mail.py
iposi/settings.py
iposi-0.1.0.dist-info/LICENSE.txt
iposi-0.1.0.dist-info/METADATA
iposi-0.1.0.dist-info/WHEEL
iposi-0.1.0.dist-info/top_level.txt
iposi-0.1.0.dist-info/RECORD
