Metadata-Version: 2.1
Name: iposi
Version: 0.1.0
Summary: Make sending emails a bit easier in Python
Author-email: "Christian Hettlage (SAAO/SALT)" <c.hettlage@saao.nrf.ac.za>
Project-URL: Homepage, https://github.com/saltastroops/iposi
Project-URL: Repository, https://github.com/saltastroops/iposi
Classifier: License :: OSI Approved :: MIT License
Requires-Python: >=3.9
License-File: LICENSE.txt
Requires-Dist: pydantic >=2.7.4
Requires-Dist: pydantic-settings >=2.3.2
